easy_twitter_crawler/__init__.py
easy_twitter_crawler/twitter_crawler/__init__.py
easy_twitter_crawler/twitter_crawler/constants.py
easy_twitter_crawler/twitter_crawler/exceptions.py
easy_twitter_crawler/twitter_crawler/extractors.py
easy_twitter_crawler/twitter_crawler/page_iterators.py
easy_twitter_crawler/twitter_crawler/twitter_scraper.py
easy_twitter_crawler/twitter_crawler/twitter_types.py
easy_twitter_crawler/twitter_utils/__init__.py
easy_twitter_crawler/twitter_utils/twitter_filter.py
easy_twitter_crawler/twitter_utils/twitter_utils.py
easy_twitter_crawler-1.0.4.dist-info/LICENSE
easy_twitter_crawler-1.0.4.dist-info/METADATA
easy_twitter_crawler-1.0.4.dist-info/WHEEL
easy_twitter_crawler-1.0.4.dist-info/top_level.txt
easy_twitter_crawler-1.0.4.dist-info/RECORD
