Metadata-Version: 2.1
Name: easy-twitter-crawler
Version: 1.0.4
Summary: 简易、强大的推特（Twitter）采集程序,支持元搜索,用户,粉丝,关注,发文,回复,评论等采集
Home-page: https://easy-twitter-crawler.xink.top/
Author: hanxinkong
Author-email: xinkonghan@gmail.com
License: MIT
Keywords: easy,twitter,crawler,spider
Requires-Python: >=3.6.8
License-File: LICENSE
Requires-Dist: easy-spider-tool (==1.0.7)
Requires-Dist: loguru (==0.7.0)
Requires-Dist: my-fake-useragent (==0.2.1)
Requires-Dist: requests (==2.27.1)
Requires-Dist: requests-html (==0.10.0)
Requires-Dist: urllib3 (==1.26.15)
